ai2_wmd/__init__.py
ai2_wmd-0.0.1.dist-info/METADATA
ai2_wmd-0.0.1.dist-info/WHEEL
ai2_wmd-0.0.1.dist-info/RECORD
