Metadata-Version: 2.1
Name: ai2-wmd
Version: 0.0.1
Summary: 
Author: weihong.xu
Author-email: xuweihong.cn@gmail.com
Requires-Python: >=3.8,<4.0
Classifier: Programming Language :: Python :: 3
Classifier: Programming Language :: Python :: 3.8
Classifier: Programming Language :: Python :: 3.9
Classifier: Programming Language :: Python :: 3.10
Classifier: Programming Language :: Python :: 3.11
Classifier: Programming Language :: Python :: 3.12
Requires-Dist: ai2-kit (>=0.15.10,<0.16.0)
